flask_ad_auth/__init__.py
flask_ad_auth/ad_login.py
flask_ad_auth-1.1.3.dist-info/LICENSE
flask_ad_auth-1.1.3.dist-info/METADATA
flask_ad_auth-1.1.3.dist-info/WHEEL
flask_ad_auth-1.1.3.dist-info/top_level.txt
flask_ad_auth-1.1.3.dist-info/RECORD
