Metadata-Version: 2.1
Name: flask-ad-auth
Version: 1.1.3
Summary: Flask Azure Active Directory Auth
Home-page: https://github.com/wuttem/flask-ad-auth
Author: Matthias Wutte
Author-email: matthias.wutte@gmail.com
License: MIT
Classifier: Framework :: Flask
Classifier: Intended Audience :: Developers
Classifier: License :: OSI Approved :: MIT License
Classifier: Programming Language :: Python :: 3
Classifier: Topic :: System :: Systems Administration :: Authentication/Directory
License-File: LICENSE
Requires-Dist: flask
Requires-Dist: werkzeug
Requires-Dist: flask-login
Requires-Dist: requests
Requires-Dist: msal
